six_web/__init__.py
six_web/six.py
six_web-1.0.1.dist-info/DESCRIPTION.rst
six_web-1.0.1.dist-info/METADATA
six_web-1.0.1.dist-info/RECORD
six_web-1.0.1.dist-info/WHEEL
six_web-1.0.1.dist-info/metadata.json
six_web-1.0.1.dist-info/top_level.txt
