Metadata-Version: 2.0
Name: six-web
Version: 1.0.1
Summary: Micro python web framework 
Home-page: https://github.com/fish267/six-web
Author: fish267
Author-email: fsh267@gmail.com
License: MIT
Platform: any
Classifier: Development Status :: 4 - Beta
Classifier: Intended Audience :: Developers
Classifier: License :: OSI Approved :: MIT License
Classifier: Programming Language :: Python :: 3.5
